google_cloud_game_servers-1.8.3-py3.9-nspkg.pth
google/cloud/gaming/__init__.py
google/cloud/gaming/gapic_version.py
google/cloud/gaming/py.typed
google/cloud/gaming_v1/__init__.py
google/cloud/gaming_v1/gapic_metadata.json
google/cloud/gaming_v1/gapic_version.py
google/cloud/gaming_v1/py.typed
google/cloud/gaming_v1/services/__init__.py
google/cloud/gaming_v1/services/game_server_clusters_service/__init__.py
google/cloud/gaming_v1/services/game_server_clusters_service/async_client.py
google/cloud/gaming_v1/services/game_server_clusters_service/client.py
google/cloud/gaming_v1/services/game_server_clusters_service/pagers.py
google/cloud/gaming_v1/services/game_server_clusters_service/transports/__init__.py
google/cloud/gaming_v1/services/game_server_clusters_service/transports/base.py
google/cloud/gaming_v1/services/game_server_clusters_service/transports/grpc.py
google/cloud/gaming_v1/services/game_server_clusters_service/transports/grpc_asyncio.py
google/cloud/gaming_v1/services/game_server_clusters_service/transports/rest.py
google/cloud/gaming_v1/services/game_server_configs_service/__init__.py
google/cloud/gaming_v1/services/game_server_configs_service/async_client.py
google/cloud/gaming_v1/services/game_server_configs_service/client.py
google/cloud/gaming_v1/services/game_server_configs_service/pagers.py
google/cloud/gaming_v1/services/game_server_configs_service/transports/__init__.py
google/cloud/gaming_v1/services/game_server_configs_service/transports/base.py
google/cloud/gaming_v1/services/game_server_configs_service/transports/grpc.py
google/cloud/gaming_v1/services/game_server_configs_service/transports/grpc_asyncio.py
google/cloud/gaming_v1/services/game_server_configs_service/transports/rest.py
google/cloud/gaming_v1/services/game_server_deployments_service/__init__.py
google/cloud/gaming_v1/services/game_server_deployments_service/async_client.py
google/cloud/gaming_v1/services/game_server_deployments_service/client.py
google_cloud_game_servers-1.8.3.dist-info/LICENSE
google_cloud_game_servers-1.8.3.dist-info/METADATA
google_cloud_game_servers-1.8.3.dist-info/WHEEL
google_cloud_game_servers-1.8.3.dist-info/namespace_packages.txt
google_cloud_game_servers-1.8.3.dist-info/top_level.txt
google_cloud_game_servers-1.8.3.dist-info/RECORD
